psf_utils/__init__.py
psf_utils/list.py
psf_utils/parse.py
psf_utils/psf.py
psf_utils/show.py
psf_utils-1.9.dist-info/entry_points.txt
psf_utils-1.9.dist-info/WHEEL
psf_utils-1.9.dist-info/METADATA
psf_utils-1.9.dist-info/RECORD
