Metadata-Version: 2.4
Name: psf_utils
Version: 1.9
Summary: Cadence PSF file utilities
Keywords: cadence,spectre,PSF,simulation
Author: Ken Kundert
Author-email: psf_utils@nurdletech.com
Requires-Python: >=3.6
Classifier: Development Status :: 5 - Production/Stable
Classifier: Intended Audience :: Developers
Classifier: Intended Audience :: Science/Research
Classifier: License :: OSI Approved :: GNU General Public License v3 or later (GPLv3+)
Classifier: Natural Language :: English
Classifier: Operating System :: POSIX :: Linux
Classifier: Programming Language :: Python :: 3
Classifier: Topic :: Utilities
Classifier: Topic :: Scientific/Engineering
Requires-Dist: docopt
Requires-Dist: inform
Requires-Dist: matplotlib
Requires-Dist: numpy
Requires-Dist: ply==3.10
Requires-Dist: quantiphy
Project-URL: repository, https://github.com/kenkundert/psf_utils
